egile_mcp_client/__init__.py
egile_mcp_client/agents/__init__.py
egile_mcp_client/agents/anthropic_agent.py
egile_mcp_client/agents/base.py
egile_mcp_client/agents/openai_agent.py
egile_mcp_client/agents/xai_agent.py
egile_mcp_client/cli.py
egile_mcp_client/config.py
egile_mcp_client/mcp/__init__.py
egile_mcp_client/mcp/client.py
egile_mcp_client/mcp/connection.py
egile_mcp_client/mcp/protocol.py
egile_mcp_client/utils/__init__.py
egile_mcp_client/utils/history.py
egile_mcp_client/utils/logging.py
egile_mcp_client/web/__init__.py
egile_mcp_client/web/app.py
egile_mcp_client/web/routes.py
egile_mcp_client/web/templates/index.html
egile_mcp_client-0.1.3.dist-info/LICENSE
egile_mcp_client-0.1.3.dist-info/METADATA
egile_mcp_client-0.1.3.dist-info/WHEEL
egile_mcp_client-0.1.3.dist-info/entry_points.txt
egile_mcp_client-0.1.3.dist-info/RECORD
