Metadata-Version: 2.3
Name: egile-mcp-client
Version: 0.1.3
Summary: A comprehensive MCP client with direct connection and AI agent modes, including web interface
Keywords: mcp,model-context-protocol,client,ai,agent,chat,web
Author: Jean-Baptiste Poullet
Author-email: egile@gmail.com
Requires-Python: >=3.10
Classifier: Development Status :: 4 - Beta
Classifier: Intended Audience :: Developers
Classifier: License :: OSI Approved :: MIT License
Classifier: Operating System :: OS Independent
Classifier: Programming Language :: Python :: 3
Classifier: Programming Language :: Python :: 3.10
Classifier: Programming Language :: Python :: 3.11
Classifier: Programming Language :: Python :: 3.12
Requires-Dist: aiofiles (>=23.0.0)
Requires-Dist: anthropic (>=0.8.0)
Requires-Dist: anyio (>=4.4.0)
Requires-Dist: asyncio-mqtt (>=0.11.0)
Requires-Dist: click (>=8.0.0)
Requires-Dist: fastapi (>=0.115.0)
Requires-Dist: httpx (>=0.25.0)
Requires-Dist: jinja2 (>=3.1.0)
Requires-Dist: openai (>=1.0.0)
Requires-Dist: pydantic (>=2.0.0)
Requires-Dist: python-dotenv (>=1.1.1,<2.0.0)
Requires-Dist: python-multipart (>=0.0.18)
Requires-Dist: pyyaml (>=6.0.0)
Requires-Dist: rich (>=13.0.0)
Requires-Dist: sse-starlette (>=1.6.0)
Requires-Dist: typer (>=0.9.0)
Requires-Dist: uvicorn (>=0.24.0)
Requires-Dist: websockets (>=11.0.0)
Project-URL: Homepage, https://github.com/jpoullet2000/egile-mcp-client
Project-URL: Repository, https://github.com/jpoullet2000/egile-mcp-client
